setup.py
always320/__init__.py
always320/downloader.py
always320/get320.py
always320/parseyoutube.py
always320/vubey_api.py
always320.egg-info/PKG-INFO
always320.egg-info/SOURCES.txt
always320.egg-info/dependency_links.txt
always320.egg-info/entry_points.txt
always320.egg-info/requires.txt
always320.egg-info/top_level.txt