Metadata-Version: 1.0
Name: always320
Version: 0.2.11
Summary: UNKNOWN
Home-page: UNKNOWN
Author: ['Parth Parikh', 'Sanket Patel']
Author-email: ['parthpower@gmail.com', 'sanketplus@gmail.com']
License: UNKNOWN
Platform: UNKNOWN
